tasktiger/__init__.py
tasktiger/_internal.py
tasktiger/exceptions.py
tasktiger/flask_script.py
tasktiger/logging.py
tasktiger/redis_lock.py
tasktiger/redis_scripts.py
tasktiger/redis_semaphore.py
tasktiger/retry.py
tasktiger/rollbar.py
tasktiger/schedule.py
tasktiger/stats.py
tasktiger/task.py
tasktiger/tasktiger.py
tasktiger/test_helpers.py
tasktiger/timeouts.py
tasktiger/worker.py
tasktiger/lua/execute_pipeline.lua
tasktiger/lua/semaphore.lua
tasktiger-0.10.1.dist-info/LICENSE
tasktiger-0.10.1.dist-info/METADATA
tasktiger-0.10.1.dist-info/WHEEL
tasktiger-0.10.1.dist-info/entry_points.txt
tasktiger-0.10.1.dist-info/top_level.txt
tasktiger-0.10.1.dist-info/RECORD
